README.rst
setup.py
sourblossom/__init__.py
sourblossom/blob.py
sourblossom/framing.py
sourblossom/perftest.py
sourblossom/pickler.py
sourblossom/pool.py
sourblossom/router.py
sourblossom/rpc.py
sourblossom/test_blob.py
sourblossom/test_framing.py
sourblossom/test_pickler.py
sourblossom/test_pool.py
sourblossom/test_router.py
sourblossom/test_rpc.py
sourblossom/test_tools.py
sourblossom/tools.py
sourblossom.egg-info/PKG-INFO
sourblossom.egg-info/SOURCES.txt
sourblossom.egg-info/dependency_links.txt
sourblossom.egg-info/requires.txt
sourblossom.egg-info/top_level.txt