Metadata-Version: 1.0
Name: sourblossom
Version: 0.1.0
Summary: Asynchronous remote procedure call library
Home-page: https://github.com/smurn/sourblossom
Author: Stefan C. Mueller
Author-email: stefan.mueller@fhnw.ch
License: UNKNOWN
Platform: UNKNOWN
